{
  "version": "7",
  "dialect": "postgresql",
  "entries": [
    {
      "idx": 0,
      "version": "7",
      "when": 1755180205061,
      "tag": "0000_redundant_rhodey",
      "breakpoints": true
    },
    {
      "idx": 1,
      "version": "7",
      "when": 1755180840053,
      "tag": "0001_flowery_the_leader",
      "breakpoints": true
    },
    {
      "idx": 2,
      "version": "7",
      "when": 1755181876756,
      "tag": "0002_flat_the_fury",
      "breakpoints": true
    },
    {
      "idx": 3,
      "version": "7",
      "when": 1755189758555,
      "tag": "0003_material_mad_thinker",
      "breakpoints": true
    }
  ]
}